galactory/__init__.py
galactory/__main__.py
galactory/constants.py
galactory/iter_tar.py
galactory/models.py
galactory/root.py
galactory/upstream.py
galactory/utilities.py
galactory/api/__init__.py
galactory/api/v2/__init__.py
galactory/api/v2/collection_imports.py
galactory/api/v2/collections.py
galactory/api/v3/__init__.py
galactory/api/v3/collection_imports.py
galactory/api/v3/collections.py
galactory/download/__init__.py
galactory/download/download.py
galactory/health/__init__.py
galactory/health/v1/__init__.py
galactory/health/v1/health_checks.py
tests/__init__.py
tests/conftest.py
tests/integration/conftest.py
tests/integration/test_me.py
tests/unit/__init__.py
tests/unit/conftest.py
tests/unit/client/conftest.py
tests/unit/client/test_api.py
tests/unit/client/test_health.py
tests/unit/client/test_root.py
tests/unit/models/conftest.py
tests/unit/models/test_collectioncollection.py
tests/unit/models/test_collectiondata.py
tests/unit/models/test_collectiongroup.py
tests/unit/utilities/test_discover_collections.py
tests/unit/utilities/test_incoming_collection_stream.py
galactory-0.11.2.dist-info/LICENSE
galactory-0.11.2.dist-info/METADATA
galactory-0.11.2.dist-info/WHEEL
galactory-0.11.2.dist-info/top_level.txt
galactory-0.11.2.dist-info/RECORD
