Metadata-Version: 2.1
Name: galactory
Version: 0.11.2
Summary: Ansible Galaxy proxy using Artifactory as a backend
Author: Brian Scholer
Maintainer: Brian Scholer
License: GNU GENERAL PUBLIC LICENSE
Project-URL: Repository, https://github.com/briantist/galactory
Project-URL: Changelog, https://github.com/briantist/galactory/blob/main/CHANGELOG.rst
Project-URL: Issues, https://github.com/briantist/galactory/issues
Keywords: ansible,galaxy,artifactory
Classifier: Development Status :: 4 - Beta
Classifier: License :: OSI Approved :: GNU General Public License v3 or later (GPLv3+)
Classifier: Programming Language :: Python :: 3
Classifier: Programming Language :: Python :: 3 :: Only
Classifier: Programming Language :: Python :: 3.8
Classifier: Programming Language :: Python :: 3.9
Classifier: Programming Language :: Python :: 3.10
Classifier: Programming Language :: Python :: 3.11
Requires-Python: >=3.8
License-File: LICENSE
Requires-Dist: dohq-artifactory <0.10,>=0.9
Requires-Dist: Flask <3,>=2.1
Requires-Dist: semver <4,>=2
Requires-Dist: base64io <2,>=1
Requires-Dist: ConfigArgParse <2,>=1.5
Requires-Dist: requests <3,>=2.26.0
Requires-Dist: brotli <2,>=1
Provides-Extra: tests
Requires-Dist: pytest <8,>=7.1 ; extra == 'tests'
Requires-Dist: pytest-cov ; extra == 'tests'
Requires-Dist: pytest-mock ; extra == 'tests'
Requires-Dist: coverage ; extra == 'tests'
